funniest_roncaglionidaniele_new/__init__.py
funniest_roncaglionidaniele_new/joke.py
funniest_roncaglionidaniele_new-0.1.dist-info/METADATA
funniest_roncaglionidaniele_new-0.1.dist-info/WHEEL
funniest_roncaglionidaniele_new-0.1.dist-info/top_level.txt
funniest_roncaglionidaniele_new-0.1.dist-info/RECORD
