Metadata-Version: 2.1
Name: funniest-roncaglionidaniele-new
Version: 0.1
Summary: The funniest joke in the world
Home-page: UNKNOWN
Author: Daniele Roncaglioni
Author-email: daniler@propulsionacademy.ch
License: MIT
Platform: UNKNOWN
